{
  "credit": "Made with Blockbench",
  "textures": {
    "3": "shr:items/lightningbolt",
    "4": "shr:items/ringtexture",
    "5": "shr:items/flashringred"
  },
  "elements": [
    {
      "from": [
        7.7609,
        8.71732,
        6.1051
      ],
      "to": [
        8,
        8.89664,
        6.29638
      ],
      "faces": {
        "north": {
          "uv": [
            0,
            0,
            1,
            1
          ],
          "texture": "#4"
        },
        "east": {
          "uv": [
            0,
            0,
            1,
            1
          ],
          "texture": "#4"
        },
        "south": {
          "uv": [
            0,
            0,
            1,
            1
          ],
          "texture": "#4"
        },
        "west": {
          "uv": [
            0,
            0,
            1,
            1
          ],
          "texture": "#4"
        },
        "up": {
          "uv": [
            0,
            0,
            1,
            1
          ],
          "texture": "#4"
        },
        "down": {
          "uv": [
            0,
            0,
            1,
            1
          ],
          "texture": "#4"
        }
      }
    },
    {
      "from": [
        7.57665,
        8.75396,
        6.1051
      ],
      "to": [
        7.81575,
        8.93329,
        6.29638
      ],
      "rotation": {
        "angle": -22.5,
        "axis": "z",
        "origin": [
          7.69619,
          8.87351,
          6.20671
        ]
      },
      "faces": {
        "north": {
          "uv": [
            0,
            0,
            1,
            1
          ],
          "texture": "#4"
        },
        "east": {
          "uv": [
            0,
            0,
            1,
            1
          ],
          "texture": "#4"
        },
        "south": {
          "uv": [
            0,
            0,
            1,
            1
          ],
          "texture": "#4"
        },
        "west": {
          "uv": [
            0,
            0,
            1,
            1
          ],
          "texture": "#4"
        },
        "up": {
          "uv": [
            0,
            0,
            1,
            1
          ],
          "texture": "#4"
        },
        "down": {
          "uv": [
            0,
            0,
            1,
            1
          ],
          "texture": "#4"
        }
      }
    },
    {
      "from": [
        7.42044,
        8.85833,
        6.1051
      ],
      "to": [
        7.65954,
        9.03767,
        6.29638
      ],
      "rotation": {
        "angle": -45,
        "axis": "z",
        "origin": [
          7.53999,
          8.97789,
          6.20671
        ]
      },
      "faces": {
        "north": {
          "uv": [
            0,
            0,
            1,
            1
          ],
          "texture": "#4"
        },
        "east": {
          "uv": [
            0,
            0,
            1,
            1
          ],
          "texture": "#4"
        },
        "south": {
          "uv": [
            0,
            0,
            1,
            1
          ],
          "texture": "#4"
        },
        "west": {
          "uv": [
            0,
            0,
            1,
            1
          ],
          "texture": "#4"
        },
        "up": {
          "uv": [
            0,
            0,
            1,
            1
          ],
          "texture": "#4"
        },
        "down": {
          "uv": [
            0,
            0,
            1,
            1
          ],
          "texture": "#4"
        }
      }
    },
    {
      "from": [
        7.31606,
        9.01454,
        6.1051
      ],
      "to": [
        7.49539,
        9.25363,
        6.29638
      ],
      "rotation": {
        "angle": 22.5,
        "axis": "z",
        "origin": [
          7.43562,
          9.13409,
          6.20671
        ]
      },
      "faces": {
        "north": {
          "uv": [
            0,
            0,
            1,
            1
          ],
          "rotation": 270,
          "texture": "#4"
        },
        "east": {
          "uv": [
            0,
            0,
            1,
            1
          ],
          "rotation": 270,
          "texture": "#4"
        },
        "south": {
          "uv": [
            0,
            0,
            1,
            1
          ],
          "rotation": 90,
          "texture": "#4"
        },
        "west": {
          "uv": [
            0,
            0,
            1,
            1
          ],
          "rotation": 270,
          "texture": "#4"
        },
        "up": {
          "uv": [
            0,
            0,
            1,
            1
          ],
          "rotation": 90,
          "texture": "#4"
        },
        "down": {
          "uv": [
            0,
            0,
            1,
            1
          ],
          "rotation": 270,
          "texture": "#4"
        }
      }
    },
    {
      "from": [
        7.27942,
        9.19879,
        6.1051
      ],
      "to": [
        7.45875,
        9.43789,
        6.29638
      ],
      "faces": {
        "north": {
          "uv": [
            0,
            0,
            1,
            1
          ],
          "rotation": 270,
          "texture": "#4"
        },
        "east": {
          "uv": [
            0,
            0,
            1,
            1
          ],
          "rotation": 270,
          "texture": "#4"
        },
        "south": {
          "uv": [
            0,
            0,
            1,
            1
          ],
          "rotation": 90,
          "texture": "#4"
        },
        "west": {
          "uv": [
            0,
            0,
            1,
            1
          ],
          "rotation": 270,
          "texture": "#4"
        },
        "up": {
          "uv": [
            0,
            0,
            1,
            1
          ],
          "rotation": 90,
          "texture": "#4"
        },
        "down": {
          "uv": [
            0,
            0,
            1,
            1
          ],
          "rotation": 270,
          "texture": "#4"
        }
      }
    },
    {
      "from": [
        7.22456,
        9.40125,
        6.1051
      ],
      "to": [
        7.40389,
        9.64035,
        6.29638
      ],
      "rotation": {
        "angle": -22.5,
        "axis": "z",
        "origin": [
          7.34412,
          9.28169,
          6.20671
        ]
      },
      "faces": {
        "north": {
          "uv": [
            0,
            0,
            1,
            1
          ],
          "rotation": 270,
          "texture": "#4"
        },
        "east": {
          "uv": [
            0,
            0,
            1,
            1
          ],
          "rotation": 270,
          "texture": "#4"
        },
        "south": {
          "uv": [
            0,
            0,
            1,
            1
          ],
          "rotation": 90,
          "texture": "#4"
        },
        "west": {
          "uv": [
            0,
            0,
            1,
            1
          ],
          "rotation": 270,
          "texture": "#4"
        },
        "up": {
          "uv": [
            0,
            0,
            1,
            1
          ],
          "rotation": 90,
          "texture": "#4"
        },
        "down": {
          "uv": [
            0,
            0,
            1,
            1
          ],
          "rotation": 270,
          "texture": "#4"
        }
      }
    },
    {
      "from": [
        7.25137,
        9.60929,
        6.1051
      ],
      "to": [
        7.43069,
        9.84839,
        6.29638
      ],
      "rotation": {
        "angle": -45,
        "axis": "z",
        "origin": [
          7.37092,
          9.48973,
          6.20671
        ]
      },
      "faces": {
        "north": {
          "uv": [
            0,
            0,
            1,
            1
          ],
          "rotation": 270,
          "texture": "#4"
        },
        "east": {
          "uv": [
            0,
            0,
            1,
            1
          ],
          "rotation": 270,
          "texture": "#4"
        },
        "south": {
          "uv": [
            0,
            0,
            1,
            1
          ],
          "rotation": 90,
          "texture": "#4"
        },
        "west": {
          "uv": [
            0,
            0,
            1,
            1
          ],
          "rotation": 270,
          "texture": "#4"
        },
        "up": {
          "uv": [
            0,
            0,
            1,
            1
          ],
          "rotation": 90,
          "texture": "#4"
        },
        "down": {
          "uv": [
            0,
            0,
            1,
            1
          ],
          "rotation": 270,
          "texture": "#4"
        }
      }
    },
    {
      "from": [
        7.59485,
        9.6119,
        6.1051
      ],
      "to": [
        7.83395,
        9.79122,
        6.29638
      ],
      "rotation": {
        "angle": 22.5,
        "axis": "z",
        "origin": [
          7.47529,
          9.67168,
          6.20671
        ]
      },
      "faces": {
        "north": {
          "uv": [
            0,
            0,
            1,
            1
          ],
          "rotation": 180,
          "texture": "#4"
        },
        "east": {
          "uv": [
            0,
            0,
            1,
            1
          ],
          "texture": "#4"
        },
        "south": {
          "uv": [
            0,
            0,
            1,
            1
          ],
          "rotation": 180,
          "texture": "#4"
        },
        "west": {
          "uv": [
            0,
            0,
            1,
            1
          ],
          "rotation": 180,
          "texture": "#4"
        },
        "up": {
          "uv": [
            0,
            0,
            1,
            1
          ],
          "texture": "#4"
        },
        "down": {
          "uv": [
            0,
            0,
            1,
            1
          ],
          "rotation": 180,
          "texture": "#4"
        }
      }
    },
    {
      "from": [
        7.7609,
        9.74004,
        6.1051
      ],
      "to": [
        8,
        9.91938,
        6.29638
      ],
      "faces": {
        "north": {
          "uv": [
            0,
            0,
            1,
            1
          ],
          "rotation": 180,
          "texture": "#4"
        },
        "east": {
          "uv": [
            0,
            0,
            1,
            1
          ],
          "texture": "#4"
        },
        "south": {
          "uv": [
            0,
            0,
            1,
            1
          ],
          "rotation": 180,
          "texture": "#4"
        },
        "west": {
          "uv": [
            0,
            0,
            1,
            1
          ],
          "rotation": 180,
          "texture": "#4"
        },
        "up": {
          "uv": [
            0,
            0,
            1,
            1
          ],
          "texture": "#4"
        },
        "down": {
          "uv": [
            0,
            0,
            1,
            1
          ],
          "rotation": 180,
          "texture": "#4"
        }
      }
    },
    {
      "from": [
        7.94515,
        8.75396,
        6.1051
      ],
      "to": [
        8.18425,
        8.93329,
        6.29638
      ],
      "rotation": {
        "angle": 22.5,
        "axis": "z",
        "origin": [
          8.0647,
          8.87351,
          6.20671
        ]
      },
      "faces": {
        "north": {
          "uv": [
            1,
            0,
            0,
            1
          ],
          "texture": "#4"
        },
        "east": {
          "uv": [
            1,
            0,
            0,
            1
          ],
          "texture": "#4"
        },
        "south": {
          "uv": [
            1,
            0,
            0,
            1
          ],
          "texture": "#4"
        },
        "west": {
          "uv": [
            1,
            0,
            0,
            1
          ],
          "texture": "#4"
        },
        "up": {
          "uv": [
            1,
            0,
            0,
            1
          ],
          "texture": "#4"
        },
        "down": {
          "uv": [
            1,
            0,
            0,
            1
          ],
          "texture": "#4"
        }
      }
    },
    {
      "from": [
        8.10135,
        8.85833,
        6.1051
      ],
      "to": [
        8.34046,
        9.03767,
        6.29638
      ],
      "rotation": {
        "angle": 45,
        "axis": "z",
        "origin": [
          8.2209,
          8.97789,
          6.20671
        ]
      },
      "faces": {
        "north": {
          "uv": [
            1,
            0,
            0,
            1
          ],
          "texture": "#4"
        },
        "east": {
          "uv": [
            1,
            0,
            0,
            1
          ],
          "texture": "#4"
        },
        "south": {
          "uv": [
            1,
            0,
            0,
            1
          ],
          "texture": "#4"
        },
        "west": {
          "uv": [
            1,
            0,
            0,
            1
          ],
          "texture": "#4"
        },
        "up": {
          "uv": [
            1,
            0,
            0,
            1
          ],
          "texture": "#4"
        },
        "down": {
          "uv": [
            1,
            0,
            0,
            1
          ],
          "texture": "#4"
        }
      }
    },
    {
      "from": [
        8.2655,
        9.01454,
        6.1051
      ],
      "to": [
        8.44483,
        9.25363,
        6.29638
      ],
      "rotation": {
        "angle": -22.5,
        "axis": "z",
        "origin": [
          8.32528,
          9.13409,
          6.20671
        ]
      },
      "faces": {
        "north": {
          "uv": [
            0,
            1,
            1,
            0
          ],
          "rotation": 270,
          "texture": "#4"
        },
        "east": {
          "uv": [
            0,
            1,
            1,
            0
          ],
          "rotation": 270,
          "texture": "#4"
        },
        "south": {
          "uv": [
            0,
            1,
            1,
            0
          ],
          "rotation": 90,
          "texture": "#4"
        },
        "west": {
          "uv": [
            0,
            1,
            1,
            0
          ],
          "rotation": 270,
          "texture": "#4"
        },
        "up": {
          "uv": [
            0,
            1,
            1,
            0
          ],
          "rotation": 90,
          "texture": "#4"
        },
        "down": {
          "uv": [
            0,
            1,
            1,
            0
          ],
          "rotation": 270,
          "texture": "#4"
        }
      }
    },
    {
      "from": [
        8.30215,
        9.19879,
        6.1051
      ],
      "to": [
        8.48148,
        9.43789,
        6.29638
      ],
      "faces": {
        "north": {
          "uv": [
            0,
            1,
            1,
            0
          ],
          "rotation": 270,
          "texture": "#4"
        },
        "east": {
          "uv": [
            0,
            1,
            1,
            0
          ],
          "rotation": 270,
          "texture": "#4"
        },
        "south": {
          "uv": [
            0,
            1,
            1,
            0
          ],
          "rotation": 90,
          "texture": "#4"
        },
        "west": {
          "uv": [
            0,
            1,
            1,
            0
          ],
          "rotation": 270,
          "texture": "#4"
        },
        "up": {
          "uv": [
            0,
            1,
            1,
            0
          ],
          "rotation": 90,
          "texture": "#4"
        },
        "down": {
          "uv": [
            0,
            1,
            1,
            0
          ],
          "rotation": 270,
          "texture": "#4"
        }
      }
    },
    {
      "from": [
        8.357,
        9.40125,
        6.1051
      ],
      "to": [
        8.53634,
        9.64035,
        6.29638
      ],
      "rotation": {
        "angle": 22.5,
        "axis": "z",
        "origin": [
          8.41678,
          9.28169,
          6.20671
        ]
      },
      "faces": {
        "north": {
          "uv": [
            0,
            1,
            1,
            0
          ],
          "rotation": 270,
          "texture": "#4"
        },
        "east": {
          "uv": [
            0,
            1,
            1,
            0
          ],
          "rotation": 270,
          "texture": "#4"
        },
        "south": {
          "uv": [
            0,
            1,
            1,
            0
          ],
          "rotation": 90,
          "texture": "#4"
        },
        "west": {
          "uv": [
            0,
            1,
            1,
            0
          ],
          "rotation": 270,
          "texture": "#4"
        },
        "up": {
          "uv": [
            0,
            1,
            1,
            0
          ],
          "rotation": 90,
          "texture": "#4"
        },
        "down": {
          "uv": [
            0,
            1,
            1,
            0
          ],
          "rotation": 270,
          "texture": "#4"
        }
      }
    },
    {
      "from": [
        8.33019,
        9.60929,
        6.1051
      ],
      "to": [
        8.50953,
        9.84839,
        6.29638
      ],
      "rotation": {
        "angle": 45,
        "axis": "z",
        "origin": [
          8.38997,
          9.48973,
          6.20671
        ]
      },
      "faces": {
        "north": {
          "uv": [
            0,
            1,
            1,
            0
          ],
          "rotation": 270,
          "texture": "#4"
        },
        "east": {
          "uv": [
            0,
            1,
            1,
            0
          ],
          "rotation": 270,
          "texture": "#4"
        },
        "south": {
          "uv": [
            0,
            1,
            1,
            0
          ],
          "rotation": 90,
          "texture": "#4"
        },
        "west": {
          "uv": [
            0,
            1,
            1,
            0
          ],
          "rotation": 270,
          "texture": "#4"
        },
        "up": {
          "uv": [
            0,
            1,
            1,
            0
          ],
          "rotation": 90,
          "texture": "#4"
        },
        "down": {
          "uv": [
            0,
            1,
            1,
            0
          ],
          "rotation": 270,
          "texture": "#4"
        }
      }
    },
    {
      "from": [
        7.92695,
        9.6119,
        6.1051
      ],
      "to": [
        8.16605,
        9.79122,
        6.29638
      ],
      "rotation": {
        "angle": -22.5,
        "axis": "z",
        "origin": [
          8.2856,
          9.67168,
          6.20671
        ]
      },
      "faces": {
        "north": {
          "uv": [
            1,
            0,
            0,
            1
          ],
          "rotation": 180,
          "texture": "#4"
        },
        "east": {
          "uv": [
            1,
            0,
            0,
            1
          ],
          "rotation": 180,
          "texture": "#4"
        },
        "south": {
          "uv": [
            1,
            0,
            0,
            1
          ],
          "rotation": 180,
          "texture": "#4"
        },
        "west": {
          "uv": [
            1,
            0,
            0,
            1
          ],
          "texture": "#4"
        },
        "up": {
          "uv": [
            1,
            0,
            0,
            1
          ],
          "texture": "#4"
        },
        "down": {
          "uv": [
            1,
            0,
            0,
            1
          ],
          "rotation": 180,
          "texture": "#4"
        }
      }
    },
    {
      "from": [
        8.26965,
        9.33228,
        6.11662
      ],
      "to": [
        8.42505,
        9.87623,
        6.28399
      ],
      "rotation": {
        "angle": 22.5,
        "axis": "z",
        "origin": [
          8.174,
          9.51757,
          6.19431
        ]
      },
      "faces": {
        "north": {
          "uv": [
            0,
            1,
            1,
            0
          ],
          "rotation": 270,
          "texture": "#4"
        },
        "east": {
          "uv": [
            0,
            1,
            1,
            0
          ],
          "rotation": 270,
          "texture": "#4"
        },
        "south": {
          "uv": [
            0,
            1,
            1,
            0
          ],
          "rotation": 90,
          "texture": "#4"
        },
        "west": {
          "uv": [
            0,
            1,
            1,
            0
          ],
          "rotation": 270,
          "texture": "#4"
        },
        "up": {
          "uv": [
            0,
            1,
            1,
            0
          ],
          "rotation": 90,
          "texture": "#4"
        },
        "down": {
          "uv": [
            0,
            1,
            1,
            0
          ],
          "rotation": 270,
          "texture": "#4"
        }
      }
    },
    {
      "from": [
        7.33114,
        9.31715,
        6.11662
      ],
      "to": [
        7.48656,
        9.86708,
        6.28399
      ],
      "rotation": {
        "angle": -22.5,
        "axis": "z",
        "origin": [
          7.60611,
          9.50842,
          6.19431
        ]
      },
      "faces": {
        "north": {
          "uv": [
            0,
            0,
            1,
            1
          ],
          "rotation": 270,
          "texture": "#4"
        },
        "east": {
          "uv": [
            0,
            0,
            1,
            1
          ],
          "rotation": 270,
          "texture": "#4"
        },
        "south": {
          "uv": [
            0,
            0,
            1,
            1
          ],
          "rotation": 90,
          "texture": "#4"
        },
        "west": {
          "uv": [
            0,
            0,
            1,
            1
          ],
          "rotation": 270,
          "texture": "#4"
        },
        "up": {
          "uv": [
            0,
            0,
            1,
            1
          ],
          "rotation": 90,
          "texture": "#4"
        },
        "down": {
          "uv": [
            0,
            0,
            1,
            1
          ],
          "rotation": 270,
          "texture": "#4"
        }
      }
    },
    {
      "from": [
        7.7971,
        9.83876,
        5.79031
      ],
      "to": [
        7.96091,
        9.98405,
        5.92423
      ],
      "faces": {
        "north": {
          "uv": [
            0,
            0,
            1,
            1
          ],
          "texture": "#4"
        },
        "east": {
          "uv": [
            0,
            0,
            1,
            1
          ],
          "texture": "#4"
        },
        "south": {
          "uv": [
            0,
            0,
            1,
            1
          ],
          "texture": "#4"
        },
        "west": {
          "uv": [
            0,
            0,
            1,
            1
          ],
          "texture": "#4"
        },
        "up": {
          "uv": [
            0,
            0,
            1,
            1
          ],
          "texture": "#4"
        },
        "down": {
          "uv": [
            0,
            0,
            1,
            1
          ],
          "texture": "#4"
        }
      }
    },
    {
      "from": [
        7.67087,
        9.83876,
        5.81541
      ],
      "to": [
        7.83469,
        9.98405,
        5.94935
      ],
      "rotation": {
        "angle": 22.5,
        "axis": "y",
        "origin": [
          7.75278,
          9.85611,
          5.89732
        ]
      },
      "faces": {
        "north": {
          "uv": [
            0,
            0,
            1,
            1
          ],
          "texture": "#4"
        },
        "east": {
          "uv": [
            0,
            0,
            1,
            1
          ],
          "texture": "#4"
        },
        "south": {
          "uv": [
            0,
            0,
            1,
            1
          ],
          "texture": "#4"
        },
        "west": {
          "uv": [
            0,
            0,
            1,
            1
          ],
          "texture": "#4"
        },
        "up": {
          "uv": [
            0,
            0,
            1,
            1
          ],
          "texture": "#4"
        },
        "down": {
          "uv": [
            0,
            0,
            1,
            1
          ],
          "texture": "#4"
        }
      }
    },
    {
      "from": [
        7.56386,
        9.83876,
        5.88692
      ],
      "to": [
        7.72766,
        9.98405,
        6.02085
      ],
      "rotation": {
        "angle": 45,
        "axis": "y",
        "origin": [
          7.64575,
          9.85611,
          5.96883
        ]
      },
      "faces": {
        "north": {
          "uv": [
            0,
            0,
            1,
            1
          ],
          "texture": "#4"
        },
        "east": {
          "uv": [
            0,
            0,
            1,
            1
          ],
          "texture": "#4"
        },
        "south": {
          "uv": [
            0,
            0,
            1,
            1
          ],
          "texture": "#4"
        },
        "west": {
          "uv": [
            0,
            0,
            1,
            1
          ],
          "texture": "#4"
        },
        "up": {
          "uv": [
            0,
            0,
            1,
            1
          ],
          "texture": "#4"
        },
        "down": {
          "uv": [
            0,
            0,
            1,
            1
          ],
          "texture": "#4"
        }
      }
    },
    {
      "from": [
        7.49234,
        9.83876,
        5.99394
      ],
      "to": [
        7.62627,
        9.98405,
        6.15776
      ],
      "rotation": {
        "angle": -22.5,
        "axis": "y",
        "origin": [
          7.57425,
          9.85611,
          6.07585
        ]
      },
      "faces": {
        "north": {
          "uv": [
            0,
            0,
            1,
            1
          ],
          "texture": "#4"
        },
        "east": {
          "uv": [
            0,
            0,
            1,
            1
          ],
          "texture": "#4"
        },
        "south": {
          "uv": [
            0,
            0,
            1,
            1
          ],
          "texture": "#4"
        },
        "west": {
          "uv": [
            0,
            0,
            1,
            1
          ],
          "texture": "#4"
        },
        "up": {
          "uv": [
            0,
            0,
            1,
            1
          ],
          "rotation": 270,
          "texture": "#4"
        },
        "down": {
          "uv": [
            0,
            0,
            1,
            1
          ],
          "rotation": 90,
          "texture": "#4"
        }
      }
    },
    {
      "from": [
        7.46723,
        9.83876,
        6.12018
      ],
      "to": [
        7.60115,
        9.98405,
        6.28399
      ],
      "faces": {
        "north": {
          "uv": [
            0,
            0,
            1,
            1
          ],
          "texture": "#4"
        },
        "east": {
          "uv": [
            0,
            0,
            1,
            1
          ],
          "texture": "#4"
        },
        "south": {
          "uv": [
            0,
            0,
            1,
            1
          ],
          "texture": "#4"
        },
        "west": {
          "uv": [
            0,
            0,
            1,
            1
          ],
          "texture": "#4"
        },
        "up": {
          "uv": [
            0,
            0,
            1,
            1
          ],
          "rotation": 270,
          "texture": "#4"
        },
        "down": {
          "uv": [
            0,
            0,
            1,
            1
          ],
          "rotation": 90,
          "texture": "#4"
        }
      }
    },
    {
      "from": [
        7.49234,
        9.83876,
        6.24641
      ],
      "to": [
        7.62627,
        9.98405,
        6.41023
      ],
      "rotation": {
        "angle": 22.5,
        "axis": "y",
        "origin": [
          7.57425,
          9.85611,
          6.32831
        ]
      },
      "faces": {
        "north": {
          "uv": [
            0,
            0,
            1,
            1
          ],
          "texture": "#4"
        },
        "east": {
          "uv": [
            0,
            0,
            1,
            1
          ],
          "texture": "#4"
        },
        "south": {
          "uv": [
            0,
            0,
            1,
            1
          ],
          "texture": "#4"
        },
        "west": {
          "uv": [
            0,
            0,
            1,
            1
          ],
          "texture": "#4"
        },
        "up": {
          "uv": [
            0,
            0,
            1,
            1
          ],
          "rotation": 270,
          "texture": "#4"
        },
        "down": {
          "uv": [
            0,
            0,
            1,
            1
          ],
          "rotation": 90,
          "texture": "#4"
        }
      }
    },
    {
      "from": [
        7.56386,
        9.83876,
        6.35343
      ],
      "to": [
        7.69778,
        9.98405,
        6.51724
      ],
      "rotation": {
        "angle": 45,
        "axis": "y",
        "origin": [
          7.64575,
          9.85611,
          6.43533
        ]
      },
      "faces": {
        "north": {
          "uv": [
            0,
            0,
            1,
            1
          ],
          "texture": "#4"
        },
        "east": {
          "uv": [
            0,
            0,
            1,
            1
          ],
          "texture": "#4"
        },
        "south": {
          "uv": [
            0,
            0,
            1,
            1
          ],
          "texture": "#4"
        },
        "west": {
          "uv": [
            0,
            0,
            1,
            1
          ],
          "texture": "#4"
        },
        "up": {
          "uv": [
            0,
            0,
            1,
            1
          ],
          "rotation": 270,
          "texture": "#4"
        },
        "down": {
          "uv": [
            0,
            0,
            1,
            1
          ],
          "rotation": 90,
          "texture": "#4"
        }
      }
    },
    {
      "from": [
        7.67087,
        9.83876,
        6.45482
      ],
      "to": [
        7.83469,
        9.98405,
        6.58874
      ],
      "rotation": {
        "angle": -22.5,
        "axis": "y",
        "origin": [
          7.75278,
          9.85611,
          6.50683
        ]
      },
      "faces": {
        "north": {
          "uv": [
            0,
            0,
            1,
            1
          ],
          "texture": "#4"
        },
        "east": {
          "uv": [
            0,
            0,
            1,
            1
          ],
          "texture": "#4"
        },
        "south": {
          "uv": [
            0,
            0,
            1,
            1
          ],
          "texture": "#4"
        },
        "west": {
          "uv": [
            0,
            0,
            1,
            1
          ],
          "texture": "#4"
        },
        "up": {
          "uv": [
            0,
            0,
            1,
            1
          ],
          "rotation": 180,
          "texture": "#4"
        },
        "down": {
          "uv": [
            0,
            0,
            1,
            1
          ],
          "rotation": 180,
          "texture": "#4"
        }
      }
    },
    {
      "from": [
        7.7971,
        9.83876,
        6.47993
      ],
      "to": [
        7.96091,
        9.98405,
        6.61387
      ],
      "faces": {
        "north": {
          "uv": [
            0,
            0,
            1,
            1
          ],
          "texture": "#4"
        },
        "east": {
          "uv": [
            0,
            0,
            1,
            1
          ],
          "texture": "#4"
        },
        "south": {
          "uv": [
            0,
            0,
            1,
            1
          ],
          "texture": "#4"
        },
        "west": {
          "uv": [
            0,
            0,
            1,
            1
          ],
          "texture": "#4"
        },
        "up": {
          "uv": [
            0,
            0,
            1,
            1
          ],
          "rotation": 180,
          "texture": "#4"
        },
        "down": {
          "uv": [
            0,
            0,
            1,
            1
          ],
          "rotation": 180,
          "texture": "#4"
        }
      }
    },
    {
      "from": [
        7.92334,
        9.83876,
        5.81541
      ],
      "to": [
        8.08715,
        9.98405,
        5.94935
      ],
      "rotation": {
        "angle": -22.5,
        "axis": "y",
        "origin": [
          8.00525,
          9.85611,
          5.89732
        ]
      },
      "faces": {
        "north": {
          "uv": [
            1,
            0,
            2,
            1
          ],
          "texture": "#4"
        },
        "east": {
          "uv": [
            1,
            0,
            2,
            1
          ],
          "texture": "#4"
        },
        "south": {
          "uv": [
            1,
            0,
            2,
            1
          ],
          "texture": "#4"
        },
        "west": {
          "uv": [
            1,
            0,
            2,
            1
          ],
          "texture": "#4"
        },
        "up": {
          "uv": [
            1,
            0,
            2,
            1
          ],
          "texture": "#4"
        },
        "down": {
          "uv": [
            1,
            0,
            2,
            1
          ],
          "texture": "#4"
        }
      }
    },
    {
      "from": [
        8.03036,
        9.83876,
        5.88692
      ],
      "to": [
        8.19417,
        9.98405,
        6.02085
      ],
      "rotation": {
        "angle": -45,
        "axis": "y",
        "origin": [
          8.11227,
          9.85611,
          5.96883
        ]
      },
      "faces": {
        "north": {
          "uv": [
            1,
            0,
            2,
            1
          ],
          "texture": "#4"
        },
        "east": {
          "uv": [
            1,
            0,
            2,
            1
          ],
          "texture": "#4"
        },
        "south": {
          "uv": [
            1,
            0,
            2,
            1
          ],
          "texture": "#4"
        },
        "west": {
          "uv": [
            1,
            0,
            2,
            1
          ],
          "texture": "#4"
        },
        "up": {
          "uv": [
            1,
            0,
            2,
            1
          ],
          "texture": "#4"
        },
        "down": {
          "uv": [
            1,
            0,
            2,
            1
          ],
          "texture": "#4"
        }
      }
    },
    {
      "from": [
        8.13175,
        9.83876,
        5.99394
      ],
      "to": [
        8.26567,
        9.98405,
        6.15776
      ],
      "rotation": {
        "angle": 22.5,
        "axis": "y",
        "origin": [
          8.18377,
          9.85611,
          6.07585
        ]
      },
      "faces": {
        "north": {
          "uv": [
            1,
            0,
            2,
            1
          ],
          "texture": "#4"
        },
        "east": {
          "uv": [
            1,
            0,
            2,
            1
          ],
          "texture": "#4"
        },
        "south": {
          "uv": [
            1,
            0,
            2,
            1
          ],
          "texture": "#4"
        },
        "west": {
          "uv": [
            1,
            0,
            2,
            1
          ],
          "texture": "#4"
        },
        "up": {
          "uv": [
            0,
            1,
            1,
            2
          ],
          "rotation": 270,
          "texture": "#4"
        },
        "down": {
          "uv": [
            0,
            1,
            1,
            2
          ],
          "rotation": 90,
          "texture": "#4"
        }
      }
    },
    {
      "from": [
        8.15685,
        9.83876,
        6.12018
      ],
      "to": [
        8.29078,
        9.98405,
        6.28399
      ],
      "faces": {
        "north": {
          "uv": [
            1,
            0,
            2,
            1
          ],
          "texture": "#4"
        },
        "east": {
          "uv": [
            1,
            0,
            2,
            1
          ],
          "texture": "#4"
        },
        "south": {
          "uv": [
            1,
            0,
            2,
            1
          ],
          "texture": "#4"
        },
        "west": {
          "uv": [
            1,
            0,
            2,
            1
          ],
          "texture": "#4"
        },
        "up": {
          "uv": [
            0,
            1,
            1,
            2
          ],
          "rotation": 270,
          "texture": "#4"
        },
        "down": {
          "uv": [
            0,
            1,
            1,
            2
          ],
          "rotation": 90,
          "texture": "#4"
        }
      }
    },
    {
      "from": [
        8.13175,
        9.83876,
        6.24641
      ],
      "to": [
        8.26567,
        9.98405,
        6.41023
      ],
      "rotation": {
        "angle": -22.5,
        "axis": "y",
        "origin": [
          8.18377,
          9.85611,
          6.32831
        ]
      },
      "faces": {
        "north": {
          "uv": [
            1,
            0,
            2,
            1
          ],
          "texture": "#4"
        },
        "east": {
          "uv": [
            1,
            0,
            2,
            1
          ],
          "texture": "#4"
        },
        "south": {
          "uv": [
            1,
            0,
            2,
            1
          ],
          "texture": "#4"
        },
        "west": {
          "uv": [
            1,
            0,
            2,
            1
          ],
          "texture": "#4"
        },
        "up": {
          "uv": [
            0,
            1,
            1,
            2
          ],
          "rotation": 270,
          "texture": "#4"
        },
        "down": {
          "uv": [
            0,
            1,
            1,
            2
          ],
          "rotation": 90,
          "texture": "#4"
        }
      }
    },
    {
      "from": [
        8.06024,
        9.83876,
        6.35343
      ],
      "to": [
        8.19417,
        9.98405,
        6.51724
      ],
      "rotation": {
        "angle": -45,
        "axis": "y",
        "origin": [
          8.11227,
          9.85611,
          6.43533
        ]
      },
      "faces": {
        "north": {
          "uv": [
            1,
            0,
            2,
            1
          ],
          "texture": "#4"
        },
        "east": {
          "uv": [
            1,
            0,
            2,
            1
          ],
          "texture": "#4"
        },
        "south": {
          "uv": [
            1,
            0,
            2,
            1
          ],
          "texture": "#4"
        },
        "west": {
          "uv": [
            1,
            0,
            2,
            1
          ],
          "texture": "#4"
        },
        "up": {
          "uv": [
            0,
            1,
            1,
            2
          ],
          "rotation": 270,
          "texture": "#4"
        },
        "down": {
          "uv": [
            0,
            1,
            1,
            2
          ],
          "rotation": 90,
          "texture": "#4"
        }
      }
    },
    {
      "from": [
        7.92334,
        9.83876,
        6.45482
      ],
      "to": [
        8.08715,
        9.98405,
        6.58874
      ],
      "rotation": {
        "angle": 22.5,
        "axis": "y",
        "origin": [
          8.00525,
          9.85611,
          6.50683
        ]
      },
      "faces": {
        "north": {
          "uv": [
            1,
            0,
            2,
            1
          ],
          "texture": "#4"
        },
        "east": {
          "uv": [
            1,
            0,
            2,
            1
          ],
          "texture": "#4"
        },
        "south": {
          "uv": [
            1,
            0,
            2,
            1
          ],
          "texture": "#4"
        },
        "west": {
          "uv": [
            1,
            0,
            2,
            1
          ],
          "texture": "#4"
        },
        "up": {
          "uv": [
            1,
            0,
            2,
            1
          ],
          "rotation": 180,
          "texture": "#4"
        },
        "down": {
          "uv": [
            1,
            0,
            2,
            1
          ],
          "rotation": 180,
          "texture": "#4"
        }
      }
    },
    {
      "from": [
        7.64087,
        9.84457,
        5.88896
      ],
      "to": [
        8.06745,
        9.95831,
        6.51521
      ],
      "faces": {
        "north": {
          "uv": [
            1,
            0,
            2,
            1
          ],
          "texture": "#5"
        },
        "east": {
          "uv": [
            1,
            0,
            2,
            1
          ],
          "texture": "#5"
        },
        "south": {
          "uv": [
            1,
            0,
            2,
            1
          ],
          "texture": "#5"
        },
        "west": {
          "uv": [
            1,
            0,
            2,
            1
          ],
          "texture": "#5"
        },
        "up": {
          "uv": [
            0,
            1,
            1,
            2
          ],
          "rotation": 270,
          "texture": "#5"
        },
        "down": {
          "uv": [
            0,
            1,
            1,
            2
          ],
          "rotation": 90,
          "texture": "#5"
        }
      }
    },
    {
      "from": [
        7.55899,
        9.84404,
        5.93989
      ],
      "to": [
        7.66024,
        9.95779,
        6.42527
      ],
      "faces": {
        "north": {
          "uv": [
            1,
            0,
            2,
            1
          ],
          "texture": "#5"
        },
        "east": {
          "uv": [
            1,
            0,
            2,
            1
          ],
          "texture": "#5"
        },
        "south": {
          "uv": [
            1,
            0,
            2,
            1
          ],
          "texture": "#5"
        },
        "west": {
          "uv": [
            1,
            0,
            2,
            1
          ],
          "texture": "#5"
        },
        "up": {
          "uv": [
            0,
            1,
            1,
            2
          ],
          "rotation": 270,
          "texture": "#5"
        },
        "down": {
          "uv": [
            0,
            1,
            1,
            2
          ],
          "rotation": 90,
          "texture": "#5"
        }
      }
    },
    {
      "from": [
        8.06643,
        9.84404,
        5.92651
      ],
      "to": [
        8.16767,
        9.95779,
        6.42527
      ],
      "faces": {
        "north": {
          "uv": [
            1,
            0,
            2,
            1
          ],
          "texture": "#5"
        },
        "east": {
          "uv": [
            1,
            0,
            2,
            1
          ],
          "texture": "#5"
        },
        "south": {
          "uv": [
            1,
            0,
            2,
            1
          ],
          "texture": "#5"
        },
        "west": {
          "uv": [
            1,
            0,
            2,
            1
          ],
          "texture": "#5"
        },
        "up": {
          "uv": [
            0,
            1,
            1,
            2
          ],
          "rotation": 270,
          "texture": "#5"
        },
        "down": {
          "uv": [
            0,
            1,
            1,
            2
          ],
          "rotation": 90,
          "texture": "#5"
        }
      }
    },
    {
      "from": [
        7.90301,
        9.99109,
        5.79477
      ],
      "to": [
        7.9304,
        10.03218,
        6.05503
      ],
      "faces": {
        "north": {
          "uv": [
            0,
            0,
            0.25,
            1
          ],
          "texture": "#3"
        },
        "east": {
          "uv": [
            0,
            0,
            1,
            1
          ],
          "texture": "#3"
        },
        "south": {
          "uv": [
            0,
            0,
            0.25,
            1
          ],
          "texture": "#3"
        },
        "west": {
          "uv": [
            0,
            0,
            1,
            1
          ],
          "texture": "#3"
        },
        "up": {
          "uv": [
            0,
            0,
            0.25,
            1
          ],
          "texture": "#3"
        },
        "down": {
          "uv": [
            0,
            0,
            0.25,
            1
          ],
          "texture": "#3"
        }
      }
    },
    {
      "from": [
        7.1521,
        9.99205,
        5.8923
      ],
      "to": [
        7.17949,
        10.03315,
        6.18611
      ],
      "rotation": {
        "angle": -22.5,
        "axis": "y",
        "origin": [
          7.79315,
          8.06067,
          7.72917
        ]
      },
      "faces": {
        "north": {
          "uv": [
            0,
            0,
            0.25,
            1
          ],
          "texture": "#3"
        },
        "east": {
          "uv": [
            0,
            0,
            1,
            1
          ],
          "texture": "#3"
        },
        "south": {
          "uv": [
            0,
            0,
            0.25,
            1
          ],
          "texture": "#3"
        },
        "west": {
          "uv": [
            0,
            0,
            1,
            1
          ],
          "texture": "#3"
        },
        "up": {
          "uv": [
            0,
            0,
            0.25,
            1
          ],
          "texture": "#3"
        },
        "down": {
          "uv": [
            0,
            0,
            0.25,
            1
          ],
          "texture": "#3"
        }
      }
    },
    {
      "from": [
        7.90303,
        9.99099,
        6.0551
      ],
      "to": [
        7.97495,
        10.03208,
        6.0825
      ],
      "faces": {
        "north": {
          "uv": [
            0,
            0,
            1,
            1
          ],
          "texture": "#3"
        },
        "east": {
          "uv": [
            0,
            0,
            0.25,
            1
          ],
          "texture": "#3"
        },
        "south": {
          "uv": [
            0,
            0,
            1,
            1
          ],
          "texture": "#3"
        },
        "west": {
          "uv": [
            0,
            0,
            0.25,
            1
          ],
          "texture": "#3"
        },
        "up": {
          "uv": [
            0,
            0,
            0.25,
            1
          ],
          "rotation": 90,
          "texture": "#3"
        },
        "down": {
          "uv": [
            0,
            0,
            0.25,
            1
          ],
          "rotation": 270,
          "texture": "#3"
        }
      }
    },
    {
      "from": [
        7.79141,
        9.99205,
        6.05825
      ],
      "to": [
        7.85304,
        10.03315,
        6.08565
      ],
      "faces": {
        "north": {
          "uv": [
            0,
            0,
            1,
            1
          ],
          "texture": "#3"
        },
        "east": {
          "uv": [
            0,
            0,
            0.25,
            1
          ],
          "texture": "#3"
        },
        "south": {
          "uv": [
            0,
            0,
            1,
            1
          ],
          "texture": "#3"
        },
        "west": {
          "uv": [
            0,
            0,
            0.25,
            1
          ],
          "texture": "#3"
        },
        "up": {
          "uv": [
            0,
            0,
            0.25,
            1
          ],
          "rotation": 90,
          "texture": "#3"
        },
        "down": {
          "uv": [
            0,
            0,
            0.25,
            1
          ],
          "rotation": 270,
          "texture": "#3"
        }
      }
    },
    {
      "from": [
        7.86054,
        9.99109,
        6.29474
      ],
      "to": [
        7.94411,
        10.0267,
        6.37967
      ],
      "faces": {
        "north": {
          "uv": [
            0,
            0,
            0.25,
            1
          ],
          "texture": "#3"
        },
        "east": {
          "uv": [
            0,
            0,
            1,
            1
          ],
          "texture": "#3"
        },
        "south": {
          "uv": [
            0,
            0,
            0.25,
            1
          ],
          "texture": "#3"
        },
        "west": {
          "uv": [
            0,
            0,
            1,
            1
          ],
          "texture": "#3"
        },
        "up": {
          "uv": [
            0,
            0,
            0.25,
            1
          ],
          "texture": "#3"
        },
        "down": {
          "uv": [
            0,
            0,
            0.25,
            1
          ],
          "texture": "#3"
        }
      }
    },
    {
      "from": [
        7.86054,
        9.99109,
        6.29474
      ],
      "to": [
        7.90574,
        10.0267,
        6.455
      ],
      "faces": {
        "north": {
          "uv": [
            0,
            0,
            0.25,
            1
          ],
          "texture": "#3"
        },
        "east": {
          "uv": [
            0,
            0,
            1,
            1
          ],
          "texture": "#3"
        },
        "south": {
          "uv": [
            0,
            0,
            0.25,
            1
          ],
          "texture": "#3"
        },
        "west": {
          "uv": [
            0,
            0,
            1,
            1
          ],
          "texture": "#3"
        },
        "up": {
          "uv": [
            0,
            0,
            0.25,
            1
          ],
          "texture": "#3"
        },
        "down": {
          "uv": [
            0,
            0,
            0.25,
            1
          ],
          "texture": "#3"
        }
      }
    },
    {
      "from": [
        7.88658,
        9.99109,
        5.85778
      ],
      "to": [
        7.90438,
        10.0267,
        6.07283
      ],
      "faces": {
        "north": {
          "uv": [
            0,
            0,
            0.25,
            1
          ],
          "texture": "#3"
        },
        "east": {
          "uv": [
            0,
            0,
            1,
            1
          ],
          "texture": "#3"
        },
        "south": {
          "uv": [
            0,
            0,
            0.25,
            1
          ],
          "texture": "#3"
        },
        "west": {
          "uv": [
            0,
            0,
            1,
            1
          ],
          "texture": "#3"
        },
        "up": {
          "uv": [
            0,
            0,
            0.25,
            1
          ],
          "texture": "#3"
        },
        "down": {
          "uv": [
            0,
            0,
            0.25,
            1
          ],
          "texture": "#3"
        }
      }
    },
    {
      "from": [
        7.86876,
        9.99109,
        6.1879
      ],
      "to": [
        7.90164,
        10.0267,
        6.23173
      ],
      "faces": {
        "north": {
          "uv": [
            0,
            0,
            0.25,
            1
          ],
          "texture": "#3"
        },
        "east": {
          "uv": [
            0,
            0,
            1,
            1
          ],
          "texture": "#3"
        },
        "south": {
          "uv": [
            0,
            0,
            0.25,
            1
          ],
          "texture": "#3"
        },
        "west": {
          "uv": [
            0,
            0,
            1,
            1
          ],
          "texture": "#3"
        },
        "up": {
          "uv": [
            0,
            0,
            0.25,
            1
          ],
          "texture": "#3"
        },
        "down": {
          "uv": [
            0,
            0,
            0.25,
            1
          ],
          "texture": "#3"
        }
      }
    },
    {
      "from": [
        7.78657,
        9.99109,
        6.1879
      ],
      "to": [
        7.81396,
        10.0267,
        6.2509
      ],
      "faces": {
        "north": {
          "uv": [
            0,
            0,
            0.25,
            1
          ],
          "texture": "#3"
        },
        "east": {
          "uv": [
            0,
            0,
            1,
            1
          ],
          "texture": "#3"
        },
        "south": {
          "uv": [
            0,
            0,
            0.25,
            1
          ],
          "texture": "#3"
        },
        "west": {
          "uv": [
            0,
            0,
            1,
            1
          ],
          "texture": "#3"
        },
        "up": {
          "uv": [
            0,
            0,
            0.25,
            1
          ],
          "texture": "#3"
        },
        "down": {
          "uv": [
            0,
            0,
            0.25,
            1
          ],
          "texture": "#3"
        }
      }
    },
    {
      "from": [
        7.76741,
        9.99109,
        6.24954
      ],
      "to": [
        7.86465,
        10.0267,
        6.29748
      ],
      "faces": {
        "north": {
          "uv": [
            0,
            0,
            0.25,
            1
          ],
          "texture": "#3"
        },
        "east": {
          "uv": [
            0,
            0,
            1,
            1
          ],
          "texture": "#3"
        },
        "south": {
          "uv": [
            0,
            0,
            0.25,
            1
          ],
          "texture": "#3"
        },
        "west": {
          "uv": [
            0,
            0,
            1,
            1
          ],
          "texture": "#3"
        },
        "up": {
          "uv": [
            0,
            0,
            0.25,
            1
          ],
          "texture": "#3"
        },
        "down": {
          "uv": [
            0,
            0,
            0.25,
            1
          ],
          "texture": "#3"
        }
      }
    },
    {
      "from": [
        7.81396,
        9.99109,
        6.13037
      ],
      "to": [
        7.86465,
        10.0267,
        6.30158
      ],
      "faces": {
        "north": {
          "uv": [
            0,
            0,
            0.25,
            1
          ],
          "texture": "#3"
        },
        "east": {
          "uv": [
            0,
            0,
            1,
            1
          ],
          "texture": "#3"
        },
        "south": {
          "uv": [
            0,
            0,
            0.25,
            1
          ],
          "texture": "#3"
        },
        "west": {
          "uv": [
            0,
            0,
            1,
            1
          ],
          "texture": "#3"
        },
        "up": {
          "uv": [
            0,
            0,
            0.25,
            1
          ],
          "texture": "#3"
        },
        "down": {
          "uv": [
            0,
            0,
            0.25,
            1
          ],
          "texture": "#3"
        }
      }
    },
    {
      "from": [
        7.82081,
        9.99109,
        6.01941
      ],
      "to": [
        7.84548,
        10.0267,
        6.05777
      ],
      "faces": {
        "north": {
          "uv": [
            0,
            0,
            0.25,
            1
          ],
          "texture": "#3"
        },
        "east": {
          "uv": [
            0,
            0,
            1,
            1
          ],
          "texture": "#3"
        },
        "south": {
          "uv": [
            0,
            0,
            0.25,
            1
          ],
          "texture": "#3"
        },
        "west": {
          "uv": [
            0,
            0,
            1,
            1
          ],
          "texture": "#3"
        },
        "up": {
          "uv": [
            0,
            0,
            0.25,
            1
          ],
          "texture": "#3"
        },
        "down": {
          "uv": [
            0,
            0,
            0.25,
            1
          ],
          "texture": "#3"
        }
      }
    },
    {
      "from": [
        7.84,
        9.99109,
        5.94956
      ],
      "to": [
        7.86465,
        10.0267,
        5.98791
      ],
      "faces": {
        "north": {
          "uv": [
            0,
            0,
            0.25,
            1
          ],
          "texture": "#3"
        },
        "east": {
          "uv": [
            0,
            0,
            1,
            1
          ],
          "texture": "#3"
        },
        "south": {
          "uv": [
            0,
            0,
            0.25,
            1
          ],
          "texture": "#3"
        },
        "west": {
          "uv": [
            0,
            0,
            1,
            1
          ],
          "texture": "#3"
        },
        "up": {
          "uv": [
            0,
            0,
            0.25,
            1
          ],
          "texture": "#3"
        },
        "down": {
          "uv": [
            0,
            0,
            0.25,
            1
          ],
          "texture": "#3"
        }
      }
    },
    {
      "from": [
        7.86054,
        9.99109,
        6.05914
      ],
      "to": [
        7.92903,
        10.0267,
        6.19474
      ],
      "faces": {
        "north": {
          "uv": [
            0,
            0,
            0.25,
            1
          ],
          "texture": "#3"
        },
        "east": {
          "uv": [
            0,
            0,
            1,
            1
          ],
          "texture": "#3"
        },
        "south": {
          "uv": [
            0,
            0,
            0.25,
            1
          ],
          "texture": "#3"
        },
        "west": {
          "uv": [
            0,
            0,
            1,
            1
          ],
          "texture": "#3"
        },
        "up": {
          "uv": [
            0,
            0,
            0.25,
            1
          ],
          "texture": "#3"
        },
        "down": {
          "uv": [
            0,
            0,
            0.25,
            1
          ],
          "texture": "#3"
        }
      }
    },
    {
      "from": [
        7.86054,
        9.99109,
        6.05914
      ],
      "to": [
        7.95096,
        10.0267,
        6.12215
      ],
      "faces": {
        "north": {
          "uv": [
            0,
            0,
            0.25,
            1
          ],
          "texture": "#3"
        },
        "east": {
          "uv": [
            0,
            0,
            1,
            1
          ],
          "texture": "#3"
        },
        "south": {
          "uv": [
            0,
            0,
            0.25,
            1
          ],
          "texture": "#3"
        },
        "west": {
          "uv": [
            0,
            0,
            1,
            1
          ],
          "texture": "#3"
        },
        "up": {
          "uv": [
            0,
            0,
            0.25,
            1
          ],
          "texture": "#3"
        },
        "down": {
          "uv": [
            0,
            0,
            0.25,
            1
          ],
          "texture": "#3"
        }
      }
    },
    {
      "from": [
        7.86054,
        9.99109,
        5.90709
      ],
      "to": [
        7.88658,
        10.0267,
        6.51664
      ],
      "faces": {
        "north": {
          "uv": [
            0,
            0,
            0.25,
            1
          ],
          "texture": "#3"
        },
        "east": {
          "uv": [
            0,
            0,
            1,
            1
          ],
          "texture": "#3"
        },
        "south": {
          "uv": [
            0,
            0,
            0.25,
            1
          ],
          "texture": "#3"
        },
        "west": {
          "uv": [
            0,
            0,
            1,
            1
          ],
          "texture": "#3"
        },
        "up": {
          "uv": [
            0,
            0,
            0.25,
            1
          ],
          "texture": "#3"
        },
        "down": {
          "uv": [
            0,
            0,
            0.25,
            1
          ],
          "texture": "#3"
        }
      }
    },
    {
      "from": [
        7.83041,
        9.99109,
        5.98791
      ],
      "to": [
        7.86465,
        10.0267,
        6.5687
      ],
      "faces": {
        "north": {
          "uv": [
            0,
            0,
            0.25,
            1
          ],
          "texture": "#3"
        },
        "east": {
          "uv": [
            0,
            0,
            1,
            1
          ],
          "texture": "#3"
        },
        "south": {
          "uv": [
            0,
            0,
            0.25,
            1
          ],
          "texture": "#3"
        },
        "west": {
          "uv": [
            0,
            0,
            1,
            1
          ],
          "texture": "#3"
        },
        "up": {
          "uv": [
            0,
            0,
            0.25,
            1
          ],
          "texture": "#3"
        },
        "down": {
          "uv": [
            0,
            0,
            0.25,
            1
          ],
          "texture": "#3"
        }
      }
    },
    {
      "from": [
        7.88109,
        9.99109,
        5.84682
      ],
      "to": [
        7.88932,
        10.0267,
        6.47554
      ],
      "faces": {
        "north": {
          "uv": [
            0,
            0,
            0.25,
            1
          ],
          "texture": "#3"
        },
        "east": {
          "uv": [
            0,
            0,
            1,
            1
          ],
          "texture": "#3"
        },
        "south": {
          "uv": [
            0,
            0,
            0.25,
            1
          ],
          "texture": "#3"
        },
        "west": {
          "uv": [
            0,
            0,
            1,
            1
          ],
          "texture": "#3"
        },
        "up": {
          "uv": [
            0,
            0,
            0.25,
            1
          ],
          "texture": "#3"
        },
        "down": {
          "uv": [
            0,
            0,
            0.25,
            1
          ],
          "texture": "#3"
        }
      }
    },
    {
      "from": [
        7.8107,
        9.99012,
        6.29147
      ],
      "to": [
        7.83946,
        10.03121,
        6.63528
      ],
      "faces": {
        "north": {
          "uv": [
            0,
            0,
            0.25,
            1
          ],
          "texture": "#3"
        },
        "east": {
          "uv": [
            0,
            0,
            1,
            1
          ],
          "texture": "#3"
        },
        "south": {
          "uv": [
            0,
            0,
            0.25,
            1
          ],
          "texture": "#3"
        },
        "west": {
          "uv": [
            0,
            0,
            1,
            1
          ],
          "texture": "#3"
        },
        "up": {
          "uv": [
            0,
            0,
            0.25,
            1
          ],
          "texture": "#3"
        },
        "down": {
          "uv": [
            0,
            0,
            0.25,
            1
          ],
          "texture": "#3"
        }
      }
    },
    {
      "from": [
        7.28988,
        9.99008,
        6.39866
      ],
      "to": [
        7.31728,
        10.03118,
        6.74317
      ],
      "rotation": {
        "angle": -22.5,
        "axis": "y",
        "origin": [
          7.84876,
          8.0587,
          8.00679
        ]
      },
      "faces": {
        "north": {
          "uv": [
            0,
            0,
            0.25,
            1
          ],
          "texture": "#3"
        },
        "east": {
          "uv": [
            0,
            0,
            1,
            1
          ],
          "texture": "#3"
        },
        "south": {
          "uv": [
            0,
            0,
            0.25,
            1
          ],
          "texture": "#3"
        },
        "west": {
          "uv": [
            0,
            0,
            1,
            1
          ],
          "texture": "#3"
        },
        "up": {
          "uv": [
            0,
            0,
            0.25,
            1
          ],
          "texture": "#3"
        },
        "down": {
          "uv": [
            0,
            0,
            0.25,
            1
          ],
          "texture": "#3"
        }
      }
    },
    {
      "from": [
        7.74125,
        9.99194,
        6.29113
      ],
      "to": [
        7.83988,
        10.03302,
        6.31853
      ],
      "faces": {
        "north": {
          "uv": [
            0,
            0,
            1,
            1
          ],
          "texture": "#3"
        },
        "east": {
          "uv": [
            0,
            0,
            0.25,
            1
          ],
          "texture": "#3"
        },
        "south": {
          "uv": [
            0,
            0,
            1,
            1
          ],
          "texture": "#3"
        },
        "west": {
          "uv": [
            0,
            0,
            0.25,
            1
          ],
          "texture": "#3"
        },
        "up": {
          "uv": [
            0,
            0,
            0.25,
            1
          ],
          "rotation": 90,
          "texture": "#3"
        },
        "down": {
          "uv": [
            0,
            0,
            0.25,
            1
          ],
          "rotation": 270,
          "texture": "#3"
        }
      }
    },
    {
      "from": [
        7.86972,
        9.99008,
        6.29031
      ],
      "to": [
        7.97313,
        10.03117,
        6.3177
      ],
      "faces": {
        "north": {
          "uv": [
            0,
            0,
            1,
            1
          ],
          "texture": "#3"
        },
        "east": {
          "uv": [
            0,
            0,
            0.25,
            1
          ],
          "texture": "#3"
        },
        "south": {
          "uv": [
            0,
            0,
            1,
            1
          ],
          "texture": "#3"
        },
        "west": {
          "uv": [
            0,
            0,
            0.25,
            1
          ],
          "texture": "#3"
        },
        "up": {
          "uv": [
            0,
            0,
            0.25,
            1
          ],
          "rotation": 90,
          "texture": "#3"
        },
        "down": {
          "uv": [
            0,
            0,
            0.25,
            1
          ],
          "rotation": 270,
          "texture": "#3"
        }
      }
    },
    {
      "from": [
        7.08155,
        9.99195,
        6.21679
      ],
      "to": [
        7.10894,
        10.03303,
        6.45307
      ],
      "rotation": {
        "angle": -22.5,
        "axis": "y",
        "origin": [
          7.81849,
          8.06055,
          8.03037
        ]
      },
      "faces": {
        "north": {
          "uv": [
            0,
            0,
            0.25,
            1
          ],
          "texture": "#3"
        },
        "east": {
          "uv": [
            0,
            0,
            1,
            1
          ],
          "texture": "#3"
        },
        "south": {
          "uv": [
            0,
            0,
            0.25,
            1
          ],
          "texture": "#3"
        },
        "west": {
          "uv": [
            0,
            0,
            1,
            1
          ],
          "texture": "#3"
        },
        "up": {
          "uv": [
            0,
            0,
            0.25,
            1
          ],
          "texture": "#3"
        },
        "down": {
          "uv": [
            0,
            0,
            0.25,
            1
          ],
          "texture": "#3"
        }
      }
    },
    {
      "from": [
        7.19682,
        9.99056,
        6.17712
      ],
      "to": [
        7.22422,
        10.03165,
        6.41341
      ],
      "rotation": {
        "angle": -22.5,
        "axis": "y",
        "origin": [
          7.83789,
          8.05917,
          8.0181
        ]
      },
      "faces": {
        "north": {
          "uv": [
            0,
            0,
            0.25,
            1
          ],
          "texture": "#3"
        },
        "east": {
          "uv": [
            0,
            0,
            1,
            1
          ],
          "texture": "#3"
        },
        "south": {
          "uv": [
            0,
            0,
            0.25,
            1
          ],
          "texture": "#3"
        },
        "west": {
          "uv": [
            0,
            0,
            1,
            1
          ],
          "texture": "#3"
        },
        "up": {
          "uv": [
            0,
            0,
            0.25,
            1
          ],
          "texture": "#3"
        },
        "down": {
          "uv": [
            0,
            0,
            0.25,
            1
          ],
          "texture": "#3"
        }
      }
    },
    {
      "from": [
        7.89753,
        9.99109,
        6.37556
      ],
      "to": [
        7.91807,
        10.0267,
        6.4276
      ],
      "faces": {
        "north": {
          "uv": [
            0,
            0,
            0.25,
            1
          ],
          "texture": "#3"
        },
        "east": {
          "uv": [
            0,
            0,
            1,
            1
          ],
          "texture": "#3"
        },
        "south": {
          "uv": [
            0,
            0,
            0.25,
            1
          ],
          "texture": "#3"
        },
        "west": {
          "uv": [
            0,
            0,
            1,
            1
          ],
          "texture": "#3"
        },
        "up": {
          "uv": [
            0,
            0,
            0.25,
            1
          ],
          "texture": "#3"
        },
        "down": {
          "uv": [
            0,
            0,
            0.25,
            1
          ],
          "texture": "#3"
        }
      }
    }
  ],
  "display": {
    "thirdperson_righthand": {
      "rotation": [
        -90,
        0,
        0
      ],
      "translation": [
        0.75,
        -0.25,
        1.5
      ]
    },
    "thirdperson_lefthand": {
      "rotation": [
        -90,
        0,
        0
      ],
      "translation": [
        0.75,
        -0.25,
        1.5
      ]
    },
    "firstperson_righthand": {
      "rotation": [
        -31,
        0,
        0
      ],
      "translation": [
        -0.75,
        3.25,
        5.75
      ]
    },
    "firstperson_lefthand": {
      "rotation": [
        -31,
        0,
        0
      ],
      "translation": [
        -0.75,
        3.25,
        5.75
      ]
    },
    "ground": {
      "translation": [
        0,
        -2.5,
        0.75
      ]
    },
    "gui": {
      "rotation": [
        9,
        -3,
        0
      ],
      "translation": [
        0.75,
        -5.5,
        0
      ],
      "scale": [
        4,
        4,
        4
      ]
    },
    "fixed": {
      "rotation": [
        -90,
        0,
        0
      ],
      "translation": [
        0.5,
        2.75,
        5.75
      ],
      "scale": [
        4,
        4,
        4
      ]
    }
  },
  "groups": [
    {
      "name": "ringfull",
      "children": [
        {
          "name": "ring",
          "children": [
            0,
            1,
            2,
            3,
            4,
            5,
            6,
            7,
            8,
            9,
            10,
            11,
            12,
            13,
            14,
            15,
            16,
            17
          ]
        },
        {
          "name": "ringtop",
          "children": [
            18,
            19,
            20,
            21,
            22,
            23,
            24,
            25,
            26,
            27,
            28,
            29,
            30,
            31,
            32,
            33,
            34,
            35,
            36
          ]
        },
        {
          "name": "bolt",
          "children": [
            37,
            38,
            39,
            40,
            41,
            42,
            43,
            44,
            45,
            46,
            47,
            48,
            49,
            50,
            51,
            52,
            53,
            54,
            55,
            56,
            57,
            58,
            59,
            60,
            61
          ]
        }
      ]
    }
  ]
}